eoepca_oidc/OpenIDClient.py
eoepca_oidc/__init__.py
eoepca_oidc/main.py
eoepca_oidc-0.0.3.dist-info/LICENSE
eoepca_oidc-0.0.3.dist-info/METADATA
eoepca_oidc-0.0.3.dist-info/WHEEL
eoepca_oidc-0.0.3.dist-info/top_level.txt
eoepca_oidc-0.0.3.dist-info/RECORD
