Metadata-Version: 2.1
Name: eoepca-oidc
Version: 0.0.3
Summary: Open ID Connect python library developed by the EOEPCA team
Home-page: https://github.com/EOEPCA/um-common-oidc-client
Author: EOEPCA
Author-email: alvaro.villanueva@deimos-space.com
License: apache-2.0
Keywords: OIDC,EOEPCA,client
Platform: UNKNOWN
Classifier: Development Status :: 3 - Alpha
Classifier: Intended Audience :: Developers
Classifier: Topic :: Software Development :: Build Tools
Requires-Python: >=3.6
License-File: LICENSE
